samtool/__init__.py
samtool/main.py
samtool/utils.py
samtool-0.0.2.dist-info/LICENSE
samtool-0.0.2.dist-info/METADATA
samtool-0.0.2.dist-info/WHEEL
samtool-0.0.2.dist-info/top_level.txt
samtool-0.0.2.dist-info/RECORD
