Metadata-Version: 2.1
Name: samtool
Version: 0.0.2
Summary: SamTool is a Python library designed for easy integration of the SAM (Segment Anything with Masking) model into computer vision projects. SAM is a state-of-the-art model for segmenting objects in images with high accuracy.
Home-page: https://github.com/manbehindthemadness/samtool
Author: Manbehindthemadness
Author-email: manbehindthemadness@gmail.com
Classifier: Programming Language :: Python :: 3
Classifier: License :: OSI Approved :: MIT License
Classifier: Operating System :: OS Independent
Requires-Python: >=3.10
License-File: LICENSE
Requires-Dist: pyyaml
Requires-Dist: tqdm
Requires-Dist: numpy
Requires-Dist: matplotlib
Requires-Dist: opencv-python >=3.4.2.17
Requires-Dist: torch >=2.0.0
Requires-Dist: onnx
Requires-Dist: onnxruntime
